{
  "_class": "group",
  "booleanOperation": -1,
  "clippingMaskMode": 0,
  "do_objectID": "AEB74C45-9ADC-4E39-918D-098165D0ACB6",
  "exportOptions": {
    "_class": "exportOptions",
    "exportFormats": [
    ],
    "includedLayerIds": [
    ],
    "layerOptions": 0,
    "shouldTrim": false
  },
  "frame": {
    "_class": "rect",
    "constrainProportions": false,
    "height": 870,
    "width": 4024,
    "x": 9040,
    "y": 3
  },
  "groupLayout": {
    "_class": "MSImmutableFreeformGroupLayout"
  },
  "hasClickThrough": false,
  "hasClippingMask": false,
  "isFixedToViewport": false,
  "isFlippedHorizontal": false,
  "isFlippedVertical": false,
  "isLocked": false,
  "isVisible": true,
  "layerListExpandedType": 0,
  "layers": [
    {
      "class": "text",
      "id": "C822EDAE-4B40-4D67-94A4-B2B18B6C28FC"
    },
    {
      "class": "text",
      "id": "63B2429A-0D36-4199-AE5B-3C425C7CA275"
    },
    {
      "class": "text",
      "id": "1351D3E6-89CC-41AE-BBA1-87E49F74F5BE"
    },
    {
      "class": "text",
      "id": "68520786-F306-4A56-BD9B-D59E2C58E31B"
    },
    {
      "class": "text",
      "id": "490EB195-1D71-48A6-BFB2-008A436BF365"
    },
    {
      "class": "text",
      "id": "390A83DA-5823-405F-A4F1-8A8DD0523B20"
    },
    {
      "class": "text",
      "id": "169EC3CE-3E19-45A2-AE04-74C36EB22CA5"
    },
    {
      "class": "text",
      "id": "F5FCD722-8B04-4FA0-B855-0F17864F654F"
    },
    {
      "class": "text",
      "id": "417BE826-60A5-4200-B486-7E85D42B305E"
    },
    {
      "class": "text",
      "id": "E75F4EE4-9C6E-4AC8-BF1C-2EE64BB28160"
    },
    {
      "class": "text",
      "id": "7F1D2BF3-F511-414F-B210-AC0C4A1E75E7"
    },
    {
      "class": "text",
      "id": "BE062C1C-4DD1-434F-90B6-8F6EBEC209E3"
    }
  ],
  "name": "Right",
  "nameIsFixed": true,
  "resizingConstraint": 44,
  "resizingType": 0,
  "rotation": 0,
  "shouldBreakMaskChain": false,
  "style": {
    "_class": "style",
    "blur": {
      "_class": "blur",
      "center": "{0.5, 0.5}",
      "isEnabled": false,
      "motionAngle": 0,
      "radius": 10,
      "saturation": 1,
      "type": 0
    },
    "borderOptions": {
      "_class": "borderOptions",
      "dashPattern": [
      ],
      "isEnabled": true,
      "lineCapStyle": 0,
      "lineJoinStyle": 0
    },
    "borders": [
    ],
    "colorControls": {
      "_class": "colorControls",
      "brightness": 0,
      "contrast": 1,
      "hue": 0,
      "isEnabled": false,
      "saturation": 1
    },
    "contextSettings": {
      "_class": "graphicsContextSettings",
      "blendMode": 0,
      "opacity": 1
    },
    "do_objectID": "F59AF017-9AB4-48AC-AB46-5E34A9997DFD",
    "endMarkerType": 0,
    "fills": [
    ],
    "innerShadows": [
    ],
    "miterLimit": 10,
    "shadows": [
    ],
    "startMarkerType": 0,
    "windingRule": 1
  },
  "userInfo": {
    "com.animaapp.stc-sketch-plugin": {
      "kModelPropertiesKey": {
        "align": 3,
        "isCollapsing": 1,
        "resizesContainer": 1,
        "spacing": 32,
        "stackType": 0
      },
      "kViewTypeKey": "ADModelStackView"
    }
  }
}