{
  "_class": "group",
  "booleanOperation": -1,
  "clippingMaskMode": 0,
  "do_objectID": "56805A5A-CE5F-4114-8BF2-B1210BE84516",
  "exportOptions": {
    "_class": "exportOptions",
    "exportFormats": [
    ],
    "includedLayerIds": [
    ],
    "layerOptions": 0,
    "shouldTrim": false
  },
  "frame": {
    "_class": "rect",
    "constrainProportions": false,
    "height": 870,
    "width": 3834,
    "x": 9230,
    "y": 3
  },
  "groupLayout": {
    "_class": "MSImmutableFreeformGroupLayout"
  },
  "hasClickThrough": false,
  "hasClippingMask": false,
  "isFixedToViewport": false,
  "isFlippedHorizontal": false,
  "isFlippedVertical": false,
  "isLocked": false,
  "isVisible": true,
  "layerListExpandedType": 0,
  "layers": [
    {
      "class": "text",
      "id": "5877B09E-E8BA-42E0-8E53-4CC70C66C234"
    },
    {
      "class": "text",
      "id": "E7331002-0A4E-4CF0-8465-81E0B733D677"
    },
    {
      "class": "text",
      "id": "6B9D0D3E-7C8B-46C2-9AC6-B255BD5B24FD"
    },
    {
      "class": "text",
      "id": "2A573842-6FEF-4BE0-ADB3-29E5D8B0C7A3"
    },
    {
      "class": "text",
      "id": "44356AF4-938B-4167-8558-D715C4E243ED"
    },
    {
      "class": "text",
      "id": "C797F243-3F12-489C-9E3B-B8ABA13571D0"
    },
    {
      "class": "text",
      "id": "24CD1A49-C71E-4FC4-A4B9-EDBB25BC58E9"
    },
    {
      "class": "text",
      "id": "D287DBCF-ECD2-4CA5-9A8C-17AE089DB338"
    },
    {
      "class": "text",
      "id": "07428CA0-7CC0-41C1-BE5E-2F345B272CE1"
    },
    {
      "class": "text",
      "id": "A32266E0-CDF6-42DA-9930-1F0CA265AFC2"
    },
    {
      "class": "text",
      "id": "520E97C3-24E2-4F0D-85A4-31345C325F1B"
    },
    {
      "class": "text",
      "id": "DB32AD4F-E6A8-4ECF-9AF7-E60C997F5D70"
    }
  ],
  "name": "Right",
  "nameIsFixed": true,
  "resizingConstraint": 44,
  "resizingType": 0,
  "rotation": 0,
  "shouldBreakMaskChain": false,
  "style": {
    "_class": "style",
    "blur": {
      "_class": "blur",
      "center": "{0.5, 0.5}",
      "isEnabled": false,
      "motionAngle": 0,
      "radius": 10,
      "saturation": 1,
      "type": 0
    },
    "borderOptions": {
      "_class": "borderOptions",
      "dashPattern": [
      ],
      "isEnabled": true,
      "lineCapStyle": 0,
      "lineJoinStyle": 0
    },
    "borders": [
    ],
    "colorControls": {
      "_class": "colorControls",
      "brightness": 0,
      "contrast": 1,
      "hue": 0,
      "isEnabled": false,
      "saturation": 1
    },
    "contextSettings": {
      "_class": "graphicsContextSettings",
      "blendMode": 0,
      "opacity": 1
    },
    "do_objectID": "EC7629E7-75AA-4928-916B-AB5794B18947",
    "endMarkerType": 0,
    "fills": [
    ],
    "innerShadows": [
    ],
    "miterLimit": 10,
    "shadows": [
    ],
    "startMarkerType": 0,
    "windingRule": 1
  },
  "userInfo": {
    "com.animaapp.stc-sketch-plugin": {
      "kModelPropertiesKey": {
        "align": 3,
        "isCollapsing": 1,
        "resizesContainer": 1,
        "spacing": 32,
        "stackType": 0
      },
      "kViewTypeKey": "ADModelStackView"
    }
  }
}